{
	"info": {
		"_postman_id": "0db458fa-0ac4-4a62-83cd-7ba324b2c942",
		"name": "My Collection",
		"description": "### Welcome to Postman! This is your first collection. \n\nCollections are your starting point for building and testing APIs. You can use this one to:\n\n• Group related requests\n• Test your API in real-world scenarios\n• Document and share your requests\n\nUpdate the name and overview whenever you’re ready to make it yours.\n\n[Learn more about Postman Collections.](https://learning.postman.com/docs/collections/collections-overview/)",
		"schema": "https://schema.getpostman.com/json/collection/v2.1.0/collection.json",
		"_exporter_id": "48427592",
		"_collection_link": "https://bama1030-3081147.postman.co/workspace/Bapi-Mandal's-Workspace~a5d41357-0781-4abe-81b0-1e6fcec6ec94/collection/48427592-0db458fa-0ac4-4a62-83cd-7ba324b2c942?action=share&source=collection_link&creator=48427592"
	},
	"item": [
		{
			"name": "New Request",
			"request": {
				"auth": {
					"type": "noauth"
				},
				"method": "GET",
				"header": [],
				"url": {
					"raw": "http://localhost:8082/test",
					"protocol": "http",
					"host": [
						"localhost"
					],
					"port": "8082",
					"path": [
						"test"
					]
				}
			},
			"response": []
		},
		{
			"name": "http://localhost:8082/users/employee",
			"request": {
				"method": "POST",
				"header": [],
				"body": {
					"mode": "raw",
					"raw": "{\r\n    \"name\": \"Ramu\",\r\n    \"skills\": [\"PETTING\",\"WALKING\"],\r\n    \"daysAvailable\": [\"MONDAY\",\"WEDNESDAY\"]\r\n}",
					"options": {
						"raw": {
							"language": "json"
						}
					}
				},
				"url": {
					"raw": "http://localhost:8082/users/employee",
					"protocol": "http",
					"host": [
						"localhost"
					],
					"port": "8082",
					"path": [
						"users",
						"employee"
					]
				}
			},
			"response": []
		},
		{
			"name": "http://localhost:8082/users/employee/1",
			"request": {
				"method": "PUT",
				"header": [],
				"body": {
					"mode": "raw",
					"raw": "[\"TUESDAY\",\"WEDNESDAY\"]\r\n",
					"options": {
						"raw": {
							"language": "json"
						}
					}
				},
				"url": {
					"raw": "http://localhost:8082/users/employee/1",
					"protocol": "http",
					"host": [
						"localhost"
					],
					"port": "8082",
					"path": [
						"users",
						"employee",
						"1"
					]
				}
			},
			"response": []
		},
		{
			"name": "http://localhost:8082/users/customer/pet/1",
			"request": {
				"method": "GET",
				"header": [],
				"url": {
					"raw": "http://localhost:8082/users/customer/pet/1",
					"protocol": "http",
					"host": [
						"localhost"
					],
					"port": "8082",
					"path": [
						"users",
						"customer",
						"pet",
						"1"
					]
				}
			},
			"response": []
		},
		{
			"name": "http://localhost:8082/users/employee/1",
			"request": {
				"method": "POST",
				"header": [],
				"body": {
					"mode": "raw",
					"raw": "{\r\n    \"name\": \"Saym\",\r\n    \"skills\": [\"PETTING\",\"WALKING\"],\r\n    \"daysAvailable\": [\"MONDAY\",\"WEDNESDAY\"]\r\n}",
					"options": {
						"raw": {
							"language": "json"
						}
					}
				},
				"url": {
					"raw": "http://localhost:8082/users/employee/1",
					"protocol": "http",
					"host": [
						"localhost"
					],
					"port": "8082",
					"path": [
						"users",
						"employee",
						"1"
					]
				}
			},
			"response": []
		},
		{
			"name": "http://localhost:8082/users/employee/availability",
			"protocolProfileBehavior": {
				"disableBodyPruning": true
			},
			"request": {
				"method": "GET",
				"header": [],
				"body": {
					"mode": "raw",
					"raw": "{\r\n  \"skills\": [\"PETTING\", \"WALKING\"],\r\n  \"date\": \"2025-09-27\"\r\n}\r\n",
					"options": {
						"raw": {
							"language": "json"
						}
					}
				},
				"url": {
					"raw": "http://localhost:8082/users/employee/availability",
					"protocol": "http",
					"host": [
						"localhost"
					],
					"port": "8082",
					"path": [
						"users",
						"employee",
						"availability"
					]
				}
			},
			"response": []
		},
		{
			"name": "http://localhost:8082/users/customer",
			"request": {
				"method": "POST",
				"header": [],
				"body": {
					"mode": "raw",
					"raw": "{\r\n    \"name\": \"Shyam Mandal\",\r\n    \"phoneNumber\": \"555-1223\",\r\n    \"notes\": \"Loves......\"\r\n}",
					"options": {
						"raw": {
							"language": "json"
						}
					}
				},
				"url": {
					"raw": "http://localhost:8082/users/customer",
					"protocol": "http",
					"host": [
						"localhost"
					],
					"port": "8082",
					"path": [
						"users",
						"customer"
					]
				}
			},
			"response": []
		},
		{
			"name": "http://localhost:8082/users/customer",
			"request": {
				"method": "GET",
				"header": [],
				"url": {
					"raw": "http://localhost:8082/users/customer",
					"protocol": "http",
					"host": [
						"localhost"
					],
					"port": "8082",
					"path": [
						"users",
						"customer"
					]
				}
			},
			"response": []
		},
		{
			"name": "http://localhost:8082/pet",
			"request": {
				"method": "POST",
				"header": [],
				"body": {
					"mode": "raw",
					"raw": "{\r\n    \"type\": \"DOG\",\r\n    \"name\": \"Tommy\",\r\n    \"ownerId\": 1,\r\n    \"birthDate\": \"2025-05-10\",\r\n    \"notes\": \"Playful puppy\"\r\n}",
					"options": {
						"raw": {
							"language": "json"
						}
					}
				},
				"url": {
					"raw": "http://localhost:8082/pet",
					"protocol": "http",
					"host": [
						"localhost"
					],
					"port": "8082",
					"path": [
						"pet"
					]
				}
			},
			"response": []
		},
		{
			"name": "http://localhost:8082/pet/1",
			"request": {
				"method": "GET",
				"header": [],
				"url": {
					"raw": "http://localhost:8082/pet/1",
					"protocol": "http",
					"host": [
						"localhost"
					],
					"port": "8082",
					"path": [
						"pet",
						"1"
					]
				}
			},
			"response": []
		},
		{
			"name": "http://localhost:8082/pet/owner/1",
			"protocolProfileBehavior": {
				"disableBodyPruning": true
			},
			"request": {
				"method": "GET",
				"header": [],
				"body": {
					"mode": "raw",
					"raw": "",
					"options": {
						"raw": {
							"language": "json"
						}
					}
				},
				"url": {
					"raw": "http://localhost:8082/pet/owner/1",
					"protocol": "http",
					"host": [
						"localhost"
					],
					"port": "8082",
					"path": [
						"pet",
						"owner",
						"1"
					]
				}
			},
			"response": []
		}
	]
}